{"rates":{"btc":{"name":"Bitcoin","unit":"BTC","value":1,"type":"crypto"},"eth":{"name":"Ether","unit":"ETH","value":19.131,"type":"crypto"},"ltc":{"name":"Litecoin","unit":"LTC","value":869.485,"type":"crypto"},"bch":{"name":"Bitcoin Cash","unit":"BCH","value":151.326,"type":"crypto"},"bnb":{"name":"Binance Coin","unit":"BNB","value":110.149,"type":"crypto"},"eos":{"name":"EOS","unit":"EOS","value":97624.199,"type":"crypto"},"xrp":{"name":"XRP","unit":"XRP","value":140205.975,"type":"crypto"},"xlm":{"name":"Lumens","unit":"XLM","value":685071.174,"type":"crypto"},"link":{"name":"Chainlink","unit":"LINK","value":4417.071,"type":"crypto"},"dot":{"name":"Polkadot","unit":"DOT","value":10516.713,"type":"crypto"},"yfi":{"name":"Yearn.finance","unit":"YFI","value":10.783,"type":"crypto"},"usd":{"name":"US Dollar","unit":"$","value":67302.029,"type":"fiat"},"aed":{"name":"United Arab Emirates Dirham","unit":"DH","value":247200.69,"type":"fiat"},"ars":{"name":"Argentine Peso","unit":"$","value":60707561.817,"type":"fiat"},"aud":{"name":"Australian Dollar","unit":"A$","value":101789.204,"type":"fiat"},"bdt":{"name":"Bangladeshi Taka","unit":"৳","value":7911839.537,"type":"fiat"},"bhd":{"name":"Bahraini Dinar","unit":"BD","value":25369.432,"type":"fiat"},"bmd":{"name":"Bermudian Dollar","unit":"$","value":67302.029,"type":"fiat"},"brl":{"name":"Brazil Real","unit":"R$","value":361156.149,"type":"fiat"},"cad":{"name":"Canadian Dollar","unit":"CA$","value":92553.077,"type":"fiat"},"chf":{"name":"Swiss Franc","unit":"Fr.","value":60405.051,"type":"fiat"},"clp":{"name":"Chilean Peso","unit":"CLP$","value":62136598.593,"type":"fiat"},"cny":{"name":"Chinese Yuan","unit":"¥","value":478322.252,"type":"fiat"},"czk":{"name":"Czech Koruna","unit":"Kč","value":1548518.742,"type":"fiat"},"dkk":{"name":"Danish Krone","unit":"kr.","value":467404.046,"type":"fiat"},"eur":{"name":"Euro","unit":"€","value":62664.717,"type":"fiat"},"gbp":{"name":"British Pound Sterling","unit":"£","value":52816.142,"type":"fiat"},"gel":{"name":"Georgian Lari","unit":"₾","value":192483.803,"type":"fiat"},"hkd":{"name":"Hong Kong Dollar","unit":"HK$","value":525585.102,"type":"fiat"},"huf":{"name":"Hungarian Forint","unit":"Ft","value":24708511.184,"type":"fiat"},"idr":{"name":"Indonesian Rupiah","unit":"Rp","value":1096854262.099,"type":"fiat"},"ils":{"name":"Israeli New Shekel","unit":"₪","value":249944.661,"type":"fiat"},"inr":{"name":"Indian Rupee","unit":"₹","value":5623858.255,"type":"fiat"},"jpy":{"name":"Japanese Yen","unit":"¥","value":10589368.599,"type":"fiat"},"krw":{"name":"South Korean Won","unit":"₩","value":92685161.535,"type":"fiat"},"kwd":{"name":"Kuwaiti Dinar","unit":"KD","value":20636.821,"type":"fiat"},"lkr":{"name":"Sri Lankan Rupee","unit":"Rs","value":20422463.823,"type":"fiat"},"mmk":{"name":"Burmese Kyat","unit":"K","value":141195619.445,"type":"fiat"},"mxn":{"name":"Mexican Peso","unit":"MX$","value":1257067.304,"type":"fiat"},"myr":{"name":"Malaysian Ringgit","unit":"RM","value":317530.974,"type":"fiat"},"ngn":{"name":"Nigerian Naira","unit":"₦","value":99956583.363,"type":"fiat"},"nok":{"name":"Norwegian Krone","unit":"kr","value":719811.692,"type":"fiat"},"nzd":{"name":"New Zealand Dollar","unit":"NZ$","value":109612.459,"type":"fiat"},"php":{"name":"Philippine Peso","unit":"₱","value":3944757.289,"type":"fiat"},"pkr":{"name":"Pakistani Rupee","unit":"₨","value":18745526.483,"type":"fiat"},"pln":{"name":"Polish Zloty","unit":"zł","value":271758.998,"type":"fiat"},"rub":{"name":"Russian Ruble","unit":"₽","value":5997231.945,"type":"fiat"},"sar":{"name":"Saudi Riyal","unit":"SR","value":252440.153,"type":"fiat"},"sek":{"name":"Swedish Krona","unit":"kr","value":705755.664,"type":"fiat"},"sgd":{"name":"Singapore Dollar","unit":"S$","value":91014.755,"type":"fiat"},"thb":{"name":"Thai Baht","unit":"฿","value":2470354.638,"type":"fiat"},"try":{"name":"Turkish Lira","unit":"₺","value":2178479.129,"type":"fiat"},"twd":{"name":"New Taiwan Dollar","unit":"NT$","value":2177072.584,"type":"fiat"},"uah":{"name":"Ukrainian hryvnia","unit":"₴","value":2723775.987,"type":"fiat"},"vef":{"name":"Venezuelan bolívar fuerte","unit":"Bs.F","value":6738.952,"type":"fiat"},"vnd":{"name":"Vietnamese đồng","unit":"₫","value":1712519941.538,"type":"fiat"},"zar":{"name":"South African Rand","unit":"R","value":1250397.673,"type":"fiat"},"xdr":{"name":"IMF Special Drawing Rights","unit":"XDR","value":50758.113,"type":"fiat"},"xag":{"name":"Silver - Troy Ounce","unit":"XAG","value":2293.554,"type":"commodity"},"xau":{"name":"Gold - Troy Ounce","unit":"XAU","value":29.077,"type":"commodity"},"bits":{"name":"Bits","unit":"μBTC","value":1000000,"type":"crypto"},"sats":{"name":"Satoshi","unit":"sats","value":100000000,"type":"crypto"}}}